invoke/__init__.py
invoke/invoke.py
invoke/api/__init__.py
invoke/api/api.py
invoke/api/app/__init__.py
invoke/api/app/app_api.py
invoke/api/app/schema.py
invoke/api/boards/__init__.py
invoke/api/boards/boards_api.py
invoke/api/boards/schema.py
invoke/api/download_queue/__init__.py
invoke/api/download_queue/download_queue_api.py
invoke/api/download_queue/schema.py
invoke/api/images/__init__.py
invoke/api/images/images_api.py
invoke/api/images/schema.py
invoke/api/models/__init__.py
invoke/api/models/models_api.py
invoke/api/models/schema.py
invoke/api/queue/__init__.py
invoke/api/queue/queue_api.py
invoke/api/queue/schema.py
invoke/api/utilities/__init__.py
invoke/api/utilities/schema.py
invoke/api/utilities/utilities_api.py
invoke/graph_builder/__init__.py
invoke/graph_builder/builder.py
invoke/graph_builder/components/__init__.py
invoke/graph_builder/components/batch.py
invoke/graph_builder/components/batch_root.py
invoke/graph_builder/components/destination.py
invoke/graph_builder/components/edge.py
invoke/graph_builder/components/exposed_field.py
invoke/graph_builder/components/graph.py
invoke/graph_builder/components/position.py
invoke/graph_builder/components/source.py
invoke/graph_builder/components/workflow.py
invoke/graph_builder/components/workflow_edge.py
invoke/graph_builder/components/workflow_node.py
invoke/graph_builder/components/workflow_node_data.py
invoke/graph_builder/components/workflow_node_input.py
invoke/graph_builder/nodes/__init__.py
invoke/graph_builder/nodes/clip_skip.py
invoke/graph_builder/nodes/denoise_latents.py
invoke/graph_builder/nodes/latents_to_image.py
invoke/graph_builder/nodes/lora_loader.py
invoke/graph_builder/nodes/lora_selector.py
invoke/graph_builder/nodes/main_model_loader.py
invoke/graph_builder/nodes/node.py
invoke/graph_builder/nodes/noise.py
invoke/graph_builder/nodes/prompt.py
invoke/graph_builder/nodes/save_image.py
invoke/graph_builder/nodes/vae_loader.py
invoke/presets/__init__.py
invokeai_python-0.5.1.dist-info/LICENSE
invokeai_python-0.5.1.dist-info/METADATA
invokeai_python-0.5.1.dist-info/WHEEL
invokeai_python-0.5.1.dist-info/top_level.txt
invokeai_python-0.5.1.dist-info/RECORD
