Metadata-Version: 2.2
Name: invokeai-python
Version: 0.5.1
Summary: InvokeAI API package
Author-email: Kyle Nekto <nekto@veydlin.com>
License: MIT
Project-URL: Home, https://github.com/veydlin/invokeai-python
Classifier: Programming Language :: Python :: 3
Classifier: License :: OSI Approved :: MIT License
Classifier: Operating System :: OS Independent
Requires-Python: >=3.6
License-File: LICENSE
Requires-Dist: aiohttp>=3.0.0
Requires-Dist: pydantic>=2.0.0
